level1_design2/seq_detect_1011.v
// See LICENSE.vyoma for more details
// Verilog module for Sequence detection: 1011
module seq_detect_1011(seq_seen, inp_bit, reset, clk);

  output seq_seen;
  input inp_bit;
  input reset;
  input clk;

  parameter IDLE      = 0,
            SEQ_1     = 1, 
            SEQ_10    = 2,
            SEQ_101   = 3,
            SEQ_1011  = 4;

  reg [2:0] current_state, next_state;

  // if the current state of the FSM has the sequence 1011, then the output is high
  assign seq_seen = (current_state == SEQ_1011);

  // state transition
  always @(posedge clk)
  begin
    if(reset)
    begin
      current_state <= IDLE;
    end
    else
    begin
      current_state <= next_state;
    end
  end

  // state transition based on the input and current state
  always @(inp_bit or current_state)
  begin
    case(current_state)
      IDLE:
      begin
        if(inp_bit == 1)
          next_state = SEQ_1;
        else
          next_state = IDLE;
      end
      SEQ_1:
      begin
        if(inp_bit == 1)
          next_state = SEQ_1;
        else
          next_state = SEQ_10;
      end
      SEQ_10:
      begin
        if(inp_bit == 1)
          next_state = SEQ_101;
        else
          next_state = IDLE;
      end
      SEQ_101:
      begin
        if(inp_bit == 1)
          next_state = SEQ_1011;
        else
          next_state = SEQ_10;
      end
      SEQ_1011:
      begin
        if(inp_bit)
          next_state = SEQ_1;
        else
          next_state = SEQ_10;
      end
    endcase
  end

`ifdef COCOTB_SIM
  initial begin
    $dumpfile("dump.vcd");
    $dumpvars(0);
  end
`endif
endmodule

level1_design2/dump.vcd
$date
	Sun Jul 24 14:13:37 2022
$end
$version
	Icarus Verilog
$end
$timescale
	1ps
$end
$scope module seq_detect_1011 $end
$var wire 1 ! clk $end
$var wire 1 " inp_bit $end
$var wire 1 # reset $end
$var wire 1 $ seq_seen $end
$var reg 3 % current_state [2:0] $end
$var reg 3 & next_state [2:0] $end
$upscope $end
$enddefinitions $end
#0
$dumpvars
bx &
bx %
x$
z#
z"
z!
$end
#1
b0 &
0$
b0 %
1!
0"
1#
#5000001
0#
0!
#10000001
1!
#15000001
0!
#15000002
1!
1#
#20000002
0#
0!
#25000002
1!
#30000002
b1 &
1"
0!
#35000002
b1 %
1!
#40000002
b10 &
0"
0!
#45000002
b0 &
b10 %
1!
#50000002
b11 &
1"
0!
#55000002
b100 &
b11 %
1!
#60000002
0!
#65000002
b1 &
1$
b100 %
1!
#70000002
0!
#70000003
0$
b0 %
b0 &
1!
0"
1#
#75000003
0#
0!
#80000003
1!
#85000003
b1 &
1"
0!
#90000003
b1 %
1!
#95000003
b10 &
0"
0!
#100000003
b0 &
b10 %
1!
#105000003
0!
#110000003
b0 %
1!
#115000003
b1 &
1"
0!
#120000003
b1 %
1!
#125000003
0!
#130000003
1!
#135000003
b10 &
0"
0!
#140000003
b0 &
b10 %
1!
#145000003
0!
#150000003
b0 %
1!
#155000003
b1 &
1"
0!
#160000003
b1 %
1!
#165000003
0!
#170000003
1!
#175000003
b10 &
0"
0!
#180000003
b0 &
b10 %
1!
#185000003
b11 &
1"
0!
#190000003
b100 &
b11 %
1!
#195000003
0!
#200000003
b1 &
1$
b100 %
1!
#205000003
0!
#210000003
0$
b1 %
1!
#215000003
b10 &
0"
0!
#220000003
b0 &
b10 %
1!
#225000003
b11 &
1"
0!
#230000003
b100 &
b11 %
1!
#235000003
0!
#240000003
b1 &
1$
b100 %
1!
#245000003
0!
#250000003
0$
b1 %
1!
#255000003
0!
#260000003
1!
#265000003
0!
#270000003
1!
#275000003
b10 &
0"
0!
#280000003
b0 &
b10 %
1!
#285000003
b11 &
1"
0!
#290000003
b100 &
b11 %
1!
#295000003
b10 &
0"
0!
#300000003
b0 &
b10 %
1!
#305000003
b11 &
1"
0!
#310000003
b100 &
b11 %
1!
#315000003
b10 &
0"
0!
#320000003
b0 &
b10 %
1!
#325000003
b11 &
1"
0!
#330000003
b100 &
b11 %
1!
#335000003
b10 &
0"
0!
#340000003
b0 &
b10 %
1!
#345000003
b11 &
1"
0!
#350000003
b100 &
b11 %
1!
#355000003
b10 &
0"
0!
#360000003
b0 &
b10 %
1!
#365000003
b11 &
1"
0!
#370000003
b100 &
b11 %
1!
#375000003
0!
#380000003
b1 &
1$
b100 %
1!
#385000003
0!
#390000003
0$
b1 %
1!
